src/__init__.py
src/__main__.py
src/models.py
src/web.py
src/api/__init__.py
src/api/routes.py
src/api/websocket.py
src/auth/__init__.py
src/auth/database.py
src/auth/dingtalk.py
src/auth/jwt_handler.py
src/auth/middleware.py
src/auth/models.py
src/auth/routes.py
src/clients/__init__.py
src/clients/langbot.py
src/clients/qianxun.py
src/core/__init__.py
src/core/config_manager.py
src/core/log_collector.py
src/core/message_queue.py
src/core/state_store.py
src/handlers/__init__.py
src/handlers/message_handler.py
src/handlers/message_parser.py
src/handlers/scheduler.py
src/static/index.html
src/static/vite.svg
src/static/assets/index-CT8-YgwP.js
src/static/assets/index-CvJkSeUJ.css
src/utils/__init__.py
src/utils/text_processor.py
src/utils/xml_parser.py
forcomebot-2.2.17.dist-info/METADATA
forcomebot-2.2.17.dist-info/WHEEL
forcomebot-2.2.17.dist-info/entry_points.txt
forcomebot-2.2.17.dist-info/RECORD
