Metadata-Version: 2.4
Name: ForcomeBot
Version: 2.2.17
Summary: FORCOME 康康 - 千寻微信框架Pro与LangBot的中间件
Project-URL: Homepage, https://github.com/yourname/ForcomeBot
Project-URL: Documentation, https://github.com/yourname/ForcomeBot#readme
Project-URL: Repository, https://github.com/yourname/ForcomeBot
Author-email: Your Name <your@email.com>
License-Expression: MIT
Keywords: chatbot,langbot,middleware,onebot,qianxun,wechat
Classifier: Development Status :: 5 - Production/Stable
Classifier: Framework :: AsyncIO
Classifier: Operating System :: OS Independent
Classifier: Programming Language :: Python :: 3
Classifier: Programming Language :: Python :: 3.10
Classifier: Programming Language :: Python :: 3.11
Classifier: Programming Language :: Python :: 3.12
Classifier: Topic :: Communications :: Chat
Requires-Python: >=3.10
Requires-Dist: aiosqlite>=0.19.0
Requires-Dist: apscheduler>=3.10.0
Requires-Dist: fastapi>=0.104.0
Requires-Dist: httpx>=0.25.0
Requires-Dist: pydantic>=2.0
Requires-Dist: python-dotenv>=1.0.0
Requires-Dist: python-jose[cryptography]>=3.3.0
Requires-Dist: python-multipart>=0.0.6
Requires-Dist: pyyaml>=6.0
Requires-Dist: sqlalchemy[asyncio]>=2.0.0
Requires-Dist: uvicorn>=0.24.0
Requires-Dist: websockets>=11.0
Provides-Extra: dev
Requires-Dist: hypothesis>=6.0.0; extra == 'dev'
Requires-Dist: pytest-asyncio>=0.21.0; extra == 'dev'
Requires-Dist: pytest>=7.0.0; extra == 'dev'
